raspberry_sounds/__init__.py
raspberry_sounds/__main__.py
raspberry_sounds/sounds/15_minutes.wav
raspberry_sounds/sounds/30_minutes.wav
raspberry_sounds/sounds/5_minutes.wav
raspberry_sounds/sounds/closed.wav
raspberry_sounds/sounds/complete.wav
raspberry_sounds/sounds/one_hour.wav
raspberry_sounds-1.0.3.dist-info/licenses/LICENSE
raspberry_sounds-1.0.3.dist-info/METADATA
raspberry_sounds-1.0.3.dist-info/WHEEL
raspberry_sounds-1.0.3.dist-info/entry_points.txt
raspberry_sounds-1.0.3.dist-info/top_level.txt
raspberry_sounds-1.0.3.dist-info/RECORD
